fandas/__init__.py
fandas/cli.py
fandas/version.py
fandas/data/catalog.toml
fandas/data/standard.csv
fandas/modules/__init__.py
fandas/modules/chemical.py
fandas/modules/chemical_shift.py
fandas/modules/experiment.py
fandas/modules/input.py
fandas/modules/residue.py
fandas/modules/utils.py
fandas-2.3.0.dist-info/METADATA
fandas-2.3.0.dist-info/WHEEL
fandas-2.3.0.dist-info/entry_points.txt
fandas-2.3.0.dist-info/licenses/LICENSE
fandas-2.3.0.dist-info/RECORD
