Metadata-Version: 2.4
Name: FANDAS
Version: 2.3.0
Summary: Fast Analysis of multidimensional NMR DAta Sets
Author: Siddarth Narasimhan
Maintainer-email: "Rodrigo V. Honorato" <bonvinlab.support@uu.nl>
License-Expression: Apache-2.0
License-File: LICENSE
Classifier: Development Status :: 5 - Production/Stable
Classifier: Intended Audience :: Science/Research
Classifier: License :: OSI Approved :: Apache Software License
Classifier: Natural Language :: English
Classifier: Operating System :: MacOS
Classifier: Operating System :: POSIX
Classifier: Operating System :: POSIX :: Linux
Classifier: Programming Language :: Python :: 3.10
Classifier: Programming Language :: Python :: 3.11
Classifier: Programming Language :: Python :: 3.12
Classifier: Programming Language :: Python :: 3.13
Classifier: Topic :: Scientific/Engineering :: Bio-Informatics
Classifier: Topic :: Scientific/Engineering :: Chemistry
Requires-Python: <3.14,>3.9
Requires-Dist: numpy>=2.2.3
Requires-Dist: pandas>=2.2.2
Requires-Dist: toml>=0.10
Provides-Extra: dev
Requires-Dist: coverage; extra == 'dev'
Requires-Dist: hypothesis; extra == 'dev'
Requires-Dist: pytest; extra == 'dev'
Requires-Dist: pytest-cov; extra == 'dev'
